src/seq_detector_mealy.v
module seq_detector_mealy (
    input wire clk,
    input wire reset,
    input wire din,
    output reg dout
);
    // State encoding using parameters (Verilog-2001)
    parameter S0 = 2'b00;
    parameter S1 = 2'b01;
    parameter S2 = 2'b10;
    parameter S3 = 2'b11;
    
    reg [1:0] state, next_state;
    
    // State register
    always @(posedge clk or posedge reset) begin
        if (reset)
            state <= S0;
        else
            state <= next_state;
    end
    
    // Next state and output logic
    always @(*) begin
        dout = 1'b0; // Default output
        case (state)
            S0: begin
                next_state = din ? S1 : S0;
            end
            S1: begin
                next_state = din ? S1 : S2;
            end
            S2: begin
                next_state = din ? S3 : S0;
            end
            S3: begin
                next_state = din ? S1 : S2;
                dout = (din == 1'b0) ? 1'b1 : 1'b0;
            end
            default: next_state = S0;
        endcase
    end
endmodule

src/seq_detector_mealy_tb.v
`timescale 1ns / 1ps

module seq_detector_mealy_tb;
    reg clk, reset, din;
    wire dout;
    
    // Instantiate the sequence detector
    seq_detector_mealy dut (
        .clk(clk),
        .reset(reset),
        .din(din),
        .dout(dout)
    );
    
    // Clock generation
    initial begin
        clk = 0;
        forever #5 clk = ~clk; // 10ns period (100MHz)
    end
    
    // Stimulus
    initial begin
        // Dump waveform for debugging
        $dumpfile("seq_detector_mealy_tb.vcd");
        $dumpvars(0, seq_detector_mealy_tb);

        $monitor($time, " reset=%b, din=%b, state=%b, dout=%b", reset, din, dut.state, dout);
        reset = 1; din = 0;
        #10 reset = 0;
        // Test sequence: 11010101011
        // Expected detections: at 11010, 1101010, 110101010
        #10 din = 1;  // 1
        #10 din = 1;  // 11
        #10 din = 0;  // 110
        #10 din = 1;  // 1101
        #10 din = 0;  // 11010 (dout = 1)
        #10 din = 1;  // 110101
        #10 din = 0;  // 1101010 (dout = 1)
        #10 din = 1;  // 11010101
        #10 din = 0;  // 110101010 (dout = 1)
        #10 din = 1;  // 1101010101
        #10 din = 1;  // 11010101011
        #20 $finish;
    end
endmodule

src/seq_detector_mealy_tb.vcd
$date
	Tue May  6 21:30:05 2025
$end
$version
	Icarus Verilog
$end
$timescale
	1ps
$end
$scope module seq_detector_mealy_tb $end
$var wire 1 ! dout $end
$var reg 1 " clk $end
$var reg 1 # din $end
$var reg 1 $ reset $end
$scope module dut $end
$var wire 1 " clk $end
$var wire 1 # din $end
$var wire 1 $ reset $end
$var reg 1 ! dout $end
$var reg 2 % next_state [1:0] $end
$var reg 2 & state [1:0] $end
$upscope $end
$upscope $end
$enddefinitions $end
#0
$dumpvars
b0 &
b0 %
1$
0#
0"
0!
$end
#5000
1"
#10000
0"
0$
#15000
1"
#20000
b1 %
0"
1#
#25000
b1 &
1"
#30000
0"
#35000
1"
#40000
b10 %
0"
0#
#45000
b0 %
b10 &
1"
#50000
b11 %
0"
1#
#55000
b1 %
b11 &
1"
#60000
1!
b10 %
0"
0#
#65000
b0 %
0!
b10 &
1"
#70000
b11 %
0"
1#
#75000
b1 %
b11 &
1"
#80000
1!
b10 %
0"
0#
#85000
b0 %
0!
b10 &
1"
#90000
b11 %
0"
1#
#95000
b1 %
b11 &
1"
#100000
1!
b10 %
0"
0#
#105000
b0 %
0!
b10 &
1"
#110000
b11 %
0"
1#
#115000
b1 %
b11 &
1"
#120000
0"
#125000
b1 &
1"
